{
  "root": "f:\\project_workspace\\mosc-temp\\mosc_downloads",
  "manifest": "F:\\project_workspace\\mosc-temp\\scripts\\mosc-in-migration\\url-list.malankara-remapped.json",
  "log": [
    {
      "index": 0,
      "ok": true,
      "skipped": "exists",
      "dest": "f:\\project_workspace\\mosc-temp\\mosc_downloads\\malankara-association-2017-agenda-nominated-members-list\\2017\\Detailed-Ajanda.pdf"
    },
    {
      "index": 1,
      "ok": true,
      "skipped": "exists",
      "dest": "f:\\project_workspace\\mosc-temp\\mosc_downloads\\malankara-association-2017-agenda-nominated-members-list\\2017\\Malankara-Association-Election-Final-List-1.pdf"
    },
    {
      "index": 2,
      "ok": true,
      "skipped": "exists",
      "dest": "f:\\project_workspace\\mosc-temp\\mosc_downloads\\malankara-association-association-secretary-election-final-list-2017\\2017\\Association-Secretary-Election-Final-List.pdf"
    },
    {
      "index": 3,
      "ok": true,
      "skipped": "exists",
      "dest": "f:\\project_workspace\\mosc-temp\\mosc_downloads\\malankara-association-association-secretary-election-final-list-2017\\2017\\Managing-Committee-List-2017-22-Voters-List.pdf"
    },
    {
      "index": 4,
      "ok": true,
      "skipped": "exists",
      "dest": "f:\\project_workspace\\mosc-temp\\mosc_downloads\\malankara-association-association-secretary-election-final-list-2017\\2017\\Nadapadicramangal.pdf"
    },
    {
      "index": 5,
      "ok": true,
      "skipped": "exists",
      "dest": "f:\\project_workspace\\mosc-temp\\mosc_downloads\\malankara-association-2021\\2021\\Adoor-Kadampanad.pdf"
    },
    {
      "index": 6,
      "ok": true,
      "skipped": "exists",
      "dest": "f:\\project_workspace\\mosc-temp\\mosc_downloads\\malankara-association-2021\\2021\\Ahmedabad.pdf"
    },
    {
      "index": 7,
      "ok": true,
      "skipped": "exists",
      "dest": "f:\\project_workspace\\mosc-temp\\mosc_downloads\\malankara-association-2021\\2021\\Angamali-2.pdf"
    },
    {
      "index": 8,
      "ok": true,
      "skipped": "exists",
      "dest": "f:\\project_workspace\\mosc-temp\\mosc_downloads\\malankara-association-2021\\2021\\Association-Members-Details-Form-1.pdf"
    },
    {
      "index": 9,
      "ok": true,
      "skipped": "exists",
      "dest": "f:\\project_workspace\\mosc-temp\\mosc_downloads\\malankara-association-2021\\2021\\Bangalore.pdf"
    },
    {
      "index": 10,
      "ok": true,
      "skipped": "exists",
      "dest": "f:\\project_workspace\\mosc-temp\\mosc_downloads\\malankara-association-2021\\2021\\Bombay.pdf"
    },
    {
      "index": 11,
      "ok": true,
      "skipped": "exists",
      "dest": "f:\\project_workspace\\mosc-temp\\mosc_downloads\\malankara-association-2021\\2021\\Brahmavar.pdf"
    },
    {
      "index": 12,
      "ok": true,
      "skipped": "exists",
      "dest": "f:\\project_workspace\\mosc-temp\\mosc_downloads\\malankara-association-2021\\2021\\Calcutta.pdf"
    },
    {
      "index": 13,
      "ok": true,
      "skipped": "exists",
      "dest": "f:\\project_workspace\\mosc-temp\\mosc_downloads\\malankara-association-2021\\2021\\Chengannur.pdf"
    },
    {
      "index": 14,
      "ok": true,
      "skipped": "exists",
      "dest": "f:\\project_workspace\\mosc-temp\\mosc_downloads\\malankara-association-2021\\2021\\Delhi.pdf"
    },
    {
      "index": 15,
      "ok": true,
      "skipped": "exists",
      "dest": "f:\\project_workspace\\mosc-temp\\mosc_downloads\\malankara-association-2021\\2021\\Final-Agenda.pdf"
    },
    {
      "index": 16,
      "ok": true,
      "skipped": "exists",
      "dest": "f:\\project_workspace\\mosc-temp\\mosc_downloads\\malankara-association-2021\\2021\\Idukki.pdf"
    },
    {
      "index": 17,
      "ok": true,
      "skipped": "exists",
      "dest": "f:\\project_workspace\\mosc-temp\\mosc_downloads\\malankara-association-2021\\2021\\Kandanad-East.pdf"
    },
    {
      "index": 18,
      "ok": true,
      "skipped": "exists",
      "dest": "f:\\project_workspace\\mosc-temp\\mosc_downloads\\malankara-association-2021\\2021\\Kandanad-West.pdf"
    },
    {
      "index": 19,
      "ok": true,
      "skipped": "exists",
      "dest": "f:\\project_workspace\\mosc-temp\\mosc_downloads\\malankara-association-2021\\2021\\Kochi-1.pdf"
    },
    {
      "index": 20,
      "ok": true,
      "skipped": "exists",
      "dest": "f:\\project_workspace\\mosc-temp\\mosc_downloads\\malankara-association-2021\\2021\\Kollam.pdf"
    },
    {
      "index": 21,
      "ok": true,
      "skipped": "exists",
      "dest": "f:\\project_workspace\\mosc-temp\\mosc_downloads\\malankara-association-2021\\2021\\Kottarakkara-Punalur.pdf"
    },
    {
      "index": 22,
      "ok": true,
      "skipped": "exists",
      "dest": "f:\\project_workspace\\mosc-temp\\mosc_downloads\\malankara-association-2021\\2021\\Kottayam-Central.pdf"
    },
    {
      "index": 23,
      "ok": true,
      "skipped": "exists",
      "dest": "f:\\project_workspace\\mosc-temp\\mosc_downloads\\malankara-association-2021\\2021\\Kottayam.pdf"
    },
    {
      "index": 24,
      "ok": true,
      "skipped": "exists",
      "dest": "f:\\project_workspace\\mosc-temp\\mosc_downloads\\malankara-association-2021\\2021\\Kunnamkulam.pdf"
    },
    {
      "index": 25,
      "ok": true,
      "skipped": "exists",
      "dest": "f:\\project_workspace\\mosc-temp\\mosc_downloads\\malankara-association-2021\\2021\\Madras.pdf"
    },
    {
      "index": 26,
      "ok": true,
      "skipped": "exists",
      "dest": "f:\\project_workspace\\mosc-temp\\mosc_downloads\\malankara-association-2021\\2021\\Malabar.pdf"
    },
    {
      "index": 27,
      "ok": true,
      "skipped": "exists",
      "dest": "f:\\project_workspace\\mosc-temp\\mosc_downloads\\malankara-association-2021\\2021\\Malankara-Syrian-Christian-Association-Kalpana-2021.pdf"
    },
    {
      "index": 28,
      "ok": true,
      "skipped": "exists",
      "dest": "f:\\project_workspace\\mosc-temp\\mosc_downloads\\malankara-association-2021\\2021\\Mavelikkara.pdf"
    },
    {
      "index": 29,
      "ok": true,
      "skipped": "exists",
      "dest": "f:\\project_workspace\\mosc-temp\\mosc_downloads\\malankara-association-2021\\2021\\Nilackal.pdf"
    },
    {
      "index": 30,
      "ok": true,
      "skipped": "exists",
      "dest": "f:\\project_workspace\\mosc-temp\\mosc_downloads\\malankara-association-2021\\2021\\Niranam.pdf"
    },
    {
      "index": 31,
      "ok": true,
      "skipped": "exists",
      "dest": "f:\\project_workspace\\mosc-temp\\mosc_downloads\\malankara-association-2021\\2021\\North-East-America.pdf"
    },
    {
      "index": 32,
      "ok": true,
      "skipped": "exists",
      "dest": "f:\\project_workspace\\mosc-temp\\mosc_downloads\\malankara-association-2021\\2021\\South-West-America.pdf"
    },
    {
      "index": 33,
      "ok": true,
      "skipped": "exists",
      "dest": "f:\\project_workspace\\mosc-temp\\mosc_downloads\\malankara-association-2021\\2021\\Sulthan-Bathery.pdf"
    },
    {
      "index": 34,
      "ok": true,
      "skipped": "exists",
      "dest": "f:\\project_workspace\\mosc-temp\\mosc_downloads\\malankara-association-2021\\2021\\Thiruvananthapuram.pdf"
    },
    {
      "index": 35,
      "ok": true,
      "skipped": "exists",
      "dest": "f:\\project_workspace\\mosc-temp\\mosc_downloads\\malankara-association-2021\\2021\\Thrissur.pdf"
    },
    {
      "index": 36,
      "ok": true,
      "skipped": "exists",
      "dest": "f:\\project_workspace\\mosc-temp\\mosc_downloads\\malankara-association-2021\\2021\\Thumpamon.pdf"
    },
    {
      "index": 37,
      "ok": true,
      "skipped": "exists",
      "dest": "f:\\project_workspace\\mosc-temp\\mosc_downloads\\malankara-association-2021\\2021\\UK-Europe-Africa.pdf"
    },
    {
      "index": 38,
      "ok": true,
      "skipped": "exists",
      "dest": "f:\\project_workspace\\mosc-temp\\mosc_downloads\\malankara-association-2021\\2021\\ManagingCommitteeList2017-22.pdf"
    },
    {
      "index": 39,
      "ok": true,
      "skipped": "exists",
      "dest": "f:\\project_workspace\\mosc-temp\\mosc_downloads\\malankara-association-2021\\2021\\Agenda.pdf"
    },
    {
      "index": 40,
      "ok": true,
      "skipped": "exists",
      "dest": "f:\\project_workspace\\mosc-temp\\mosc_downloads\\malankara-association-2022\\2022\\Adoor-Kadampanad-1.pdf"
    },
    {
      "index": 41,
      "ok": true,
      "skipped": "exists",
      "dest": "f:\\project_workspace\\mosc-temp\\mosc_downloads\\malankara-association-2022\\2022\\Agenda.pdf"
    },
    {
      "index": 42,
      "ok": true,
      "skipped": "exists",
      "dest": "f:\\project_workspace\\mosc-temp\\mosc_downloads\\malankara-association-2022\\2022\\Ahmedabad-1.pdf"
    },
    {
      "index": 43,
      "ok": true,
      "skipped": "exists",
      "dest": "f:\\project_workspace\\mosc-temp\\mosc_downloads\\malankara-association-2022\\2022\\Angamali-1.pdf"
    },
    {
      "index": 44,
      "ok": true,
      "skipped": "exists",
      "dest": "f:\\project_workspace\\mosc-temp\\mosc_downloads\\malankara-association-2022\\2022\\Annex-1_RFP-Revised-Schedule.pdf"
    },
    {
      "index": 45,
      "ok": true,
      "skipped": "exists",
      "dest": "f:\\project_workspace\\mosc-temp\\mosc_downloads\\malankara-association-2022\\2022\\Association-Kalpana-32-2022.pdf"
    },
    {
      "index": 46,
      "ok": true,
      "skipped": "exists",
      "dest": "f:\\project_workspace\\mosc-temp\\mosc_downloads\\malankara-association-2022\\2022\\Association-Kalpana-English.pdf"
    },
    {
      "index": 47,
      "ok": true,
      "skipped": "exists",
      "dest": "f:\\project_workspace\\mosc-temp\\mosc_downloads\\malankara-association-2022\\2022\\Association-Members-Details-Form-2022.pdf"
    },
    {
      "index": 48,
      "ok": true,
      "skipped": "exists",
      "dest": "f:\\project_workspace\\mosc-temp\\mosc_downloads\\malankara-association-2022\\2022\\Bangalore-1.pdf"
    },
    {
      "index": 49,
      "ok": true,
      "skipped": "exists",
      "dest": "f:\\project_workspace\\mosc-temp\\mosc_downloads\\malankara-association-2022\\2022\\Bombay-1.pdf"
    },
    {
      "index": 50,
      "ok": true,
      "skipped": "exists",
      "dest": "f:\\project_workspace\\mosc-temp\\mosc_downloads\\malankara-association-2022\\2022\\Brahmavar-1.pdf"
    },
    {
      "index": 51,
      "ok": true,
      "skipped": "exists",
      "dest": "f:\\project_workspace\\mosc-temp\\mosc_downloads\\malankara-association-2022\\2022\\Calcutta-1.pdf"
    },
    {
      "index": 52,
      "ok": true,
      "skipped": "exists",
      "dest": "f:\\project_workspace\\mosc-temp\\mosc_downloads\\malankara-association-2022\\2022\\Candidates_-Episcopal-Election.pdf"
    },
    {
      "index": 53,
      "ok": true,
      "skipped": "exists",
      "dest": "f:\\project_workspace\\mosc-temp\\mosc_downloads\\malankara-association-2022\\2022\\Chengannur-1.pdf"
    },
    {
      "index": 54,
      "ok": true,
      "skipped": "exists",
      "dest": "f:\\project_workspace\\mosc-temp\\mosc_downloads\\malankara-association-2022\\2022\\Delhi-1.pdf"
    },
    {
      "index": 55,
      "ok": true,
      "skipped": "exists",
      "dest": "f:\\project_workspace\\mosc-temp\\mosc_downloads\\malankara-association-2022\\2022\\Detailed-information-of-Bishop-Candidates.pdf"
    },
    {
      "index": 56,
      "ok": true,
      "skipped": "exists",
      "dest": "f:\\project_workspace\\mosc-temp\\mosc_downloads\\malankara-association-2022\\2022\\Idukki-1.pdf"
    },
    {
      "index": 57,
      "ok": true,
      "skipped": "exists",
      "dest": "f:\\project_workspace\\mosc-temp\\mosc_downloads\\malankara-association-2022\\2022\\Kalpana-13-2022.pdf"
    },
    {
      "index": 58,
      "ok": true,
      "skipped": "exists",
      "dest": "f:\\project_workspace\\mosc-temp\\mosc_downloads\\malankara-association-2022\\2022\\Kalpana-Appt.-Monitoring-Committee.pdf"
    },
    {
      "index": 59,
      "ok": true,
      "skipped": "exists",
      "dest": "f:\\project_workspace\\mosc-temp\\mosc_downloads\\malankara-association-2022\\2022\\Kalpana-Appt.-Screening-Committee.pdf"
    },
    {
      "index": 60,
      "ok": true,
      "skipped": "exists",
      "dest": "f:\\project_workspace\\mosc-temp\\mosc_downloads\\malankara-association-2022\\2022\\Kandanad-East-1.pdf"
    },
    {
      "index": 61,
      "ok": true,
      "skipped": "exists",
      "dest": "f:\\project_workspace\\mosc-temp\\mosc_downloads\\malankara-association-2022\\2022\\Kandanad-West-1.pdf"
    },
    {
      "index": 62,
      "ok": true,
      "skipped": "exists",
      "dest": "f:\\project_workspace\\mosc-temp\\mosc_downloads\\malankara-association-2022\\2022\\Kochi-1.pdf"
    },
    {
      "index": 63,
      "ok": true,
      "skipped": "exists",
      "dest": "f:\\project_workspace\\mosc-temp\\mosc_downloads\\malankara-association-2022\\2022\\Kollam-1.pdf"
    },
    {
      "index": 64,
      "ok": true,
      "skipped": "exists",
      "dest": "f:\\project_workspace\\mosc-temp\\mosc_downloads\\malankara-association-2022\\2022\\Kottarakkara-Punalur-1.pdf"
    },
    {
      "index": 65,
      "ok": true,
      "skipped": "exists",
      "dest": "f:\\project_workspace\\mosc-temp\\mosc_downloads\\malankara-association-2022\\2022\\Kottayam-1.pdf"
    },
    {
      "index": 66,
      "ok": true,
      "skipped": "exists",
      "dest": "f:\\project_workspace\\mosc-temp\\mosc_downloads\\malankara-association-2022\\2022\\Kottayam-Central-1.pdf"
    },
    {
      "index": 67,
      "ok": true,
      "skipped": "exists",
      "dest": "f:\\project_workspace\\mosc-temp\\mosc_downloads\\malankara-association-2022\\2022\\Kunnamkulam-1.pdf"
    },
    {
      "index": 68,
      "ok": true,
      "skipped": "exists",
      "dest": "f:\\project_workspace\\mosc-temp\\mosc_downloads\\malankara-association-2022\\2022\\List-of-Candidates-Final-.pdf"
    },
    {
      "index": 69,
      "ok": true,
      "skipped": "exists",
      "dest": "f:\\project_workspace\\mosc-temp\\mosc_downloads\\malankara-association-2022\\2022\\List-of-Candidates.pdf"
    },
    {
      "index": 70,
      "ok": true,
      "skipped": "exists",
      "dest": "f:\\project_workspace\\mosc-temp\\mosc_downloads\\malankara-association-2022\\2022\\Madras-1.pdf"
    },
    {
      "index": 71,
      "ok": true,
      "skipped": "exists",
      "dest": "f:\\project_workspace\\mosc-temp\\mosc_downloads\\malankara-association-2022\\2022\\Malabar-1.pdf"
    },
    {
      "index": 72,
      "ok": true,
      "skipped": "exists",
      "dest": "f:\\project_workspace\\mosc-temp\\mosc_downloads\\malankara-association-2022\\2022\\Mavelikkara-1.pdf"
    },
    {
      "index": 73,
      "ok": true,
      "skipped": "exists",
      "dest": "f:\\project_workspace\\mosc-temp\\mosc_downloads\\malankara-association-2022\\2022\\MC-List-2017-22.pdf"
    },
    {
      "index": 74,
      "ok": true,
      "skipped": "exists",
      "dest": "f:\\project_workspace\\mosc-temp\\mosc_downloads\\malankara-association-2022\\2022\\MOSC_RFP-Commercials-Template_v1.pptx"
    },
    {
      "index": 75,
      "ok": true,
      "skipped": "exists",
      "dest": "f:\\project_workspace\\mosc-temp\\mosc_downloads\\malankara-association-2022\\2022\\MOSC_RFP-Technical-Response-Template_v1.pptx"
    },
    {
      "index": 76,
      "ok": true,
      "skipped": "exists",
      "dest": "f:\\project_workspace\\mosc-temp\\mosc_downloads\\malankara-association-2022\\2022\\Nadapadichattangal-2021.pdf"
    },
    {
      "index": 77,
      "ok": true,
      "skipped": "exists",
      "dest": "f:\\project_workspace\\mosc-temp\\mosc_downloads\\malankara-association-2022\\2022\\Nilackal-1.pdf"
    },
    {
      "index": 78,
      "ok": true,
      "skipped": "exists",
      "dest": "f:\\project_workspace\\mosc-temp\\mosc_downloads\\malankara-association-2022\\2022\\Niranam-1.pdf"
    },
    {
      "index": 79,
      "ok": true,
      "skipped": "exists",
      "dest": "f:\\project_workspace\\mosc-temp\\mosc_downloads\\malankara-association-2022\\2022\\No.-13-2022-English-Kalpana.pdf"
    },
    {
      "index": 80,
      "ok": true,
      "skipped": "exists",
      "dest": "f:\\project_workspace\\mosc-temp\\mosc_downloads\\malankara-association-2022\\2022\\Norms.pdf"
    },
    {
      "index": 81,
      "ok": true,
      "skipped": "exists",
      "dest": "f:\\project_workspace\\mosc-temp\\mosc_downloads\\malankara-association-2022\\2022\\North-East-America-1.pdf"
    },
    {
      "index": 82,
      "ok": true,
      "skipped": "exists",
      "dest": "f:\\project_workspace\\mosc-temp\\mosc_downloads\\malankara-association-2022\\2022\\Notice-Kalpana-Malankara-Association-No.-61.pdf"
    },
    {
      "index": 83,
      "ok": true,
      "skipped": "exists",
      "dest": "f:\\project_workspace\\mosc-temp\\mosc_downloads\\malankara-association-2022\\2022\\Notification.pdf"
    },
    {
      "index": 84,
      "ok": true,
      "skipped": "exists",
      "dest": "f:\\project_workspace\\mosc-temp\\mosc_downloads\\malankara-association-2022\\2022\\RFP_Virtual-Platform_Malankara-Association_v1.pdf"
    },
    {
      "index": 85,
      "ok": true,
      "skipped": "exists",
      "dest": "f:\\project_workspace\\mosc-temp\\mosc_downloads\\malankara-association-2022\\2022\\South-West-America-1.pdf"
    },
    {
      "index": 86,
      "ok": true,
      "skipped": "exists",
      "dest": "f:\\project_workspace\\mosc-temp\\mosc_downloads\\malankara-association-2022\\2022\\Sulthan-Bathery-1.pdf"
    },
    {
      "index": 87,
      "ok": true,
      "skipped": "exists",
      "dest": "f:\\project_workspace\\mosc-temp\\mosc_downloads\\malankara-association-2022\\2022\\Thiruvananthapuram-1.pdf"
    },
    {
      "index": 88,
      "ok": true,
      "skipped": "exists",
      "dest": "f:\\project_workspace\\mosc-temp\\mosc_downloads\\malankara-association-2022\\2022\\Thrissur-1.pdf"
    },
    {
      "index": 89,
      "ok": true,
      "skipped": "exists",
      "dest": "f:\\project_workspace\\mosc-temp\\mosc_downloads\\malankara-association-2022\\2022\\Thumpamon-1.pdf"
    },
    {
      "index": 90,
      "ok": true,
      "skipped": "exists",
      "dest": "f:\\project_workspace\\mosc-temp\\mosc_downloads\\malankara-association-2022\\2022\\UK-Europe-Africa-1.pdf"
    },
    {
      "index": 91,
      "ok": true,
      "skipped": "exists",
      "dest": "f:\\project_workspace\\mosc-temp\\mosc_downloads\\malankara-association-2022-2027\\2022\\Adhikarapathram.pdf"
    },
    {
      "index": 92,
      "ok": true,
      "skipped": "exists",
      "dest": "f:\\project_workspace\\mosc-temp\\mosc_downloads\\malankara-association-2022-2027\\2022\\Adoor-Kadampanad-3.pdf"
    },
    {
      "index": 93,
      "ok": true,
      "skipped": "exists",
      "dest": "f:\\project_workspace\\mosc-temp\\mosc_downloads\\malankara-association-2022-2027\\2022\\Adoor-Kadampanad.pdf"
    },
    {
      "index": 94,
      "ok": true,
      "skipped": "exists",
      "dest": "f:\\project_workspace\\mosc-temp\\mosc_downloads\\malankara-association-2022-2027\\2022\\Agenda.pdf"
    },
    {
      "index": 95,
      "ok": true,
      "skipped": "exists",
      "dest": "f:\\project_workspace\\mosc-temp\\mosc_downloads\\malankara-association-2022-2027\\2022\\Ahmedabad-3.pdf"
    },
    {
      "index": 96,
      "ok": true,
      "skipped": "exists",
      "dest": "f:\\project_workspace\\mosc-temp\\mosc_downloads\\malankara-association-2022-2027\\2022\\Ahmedabad.pdf"
    },
    {
      "index": 97,
      "ok": true,
      "skipped": "exists",
      "dest": "f:\\project_workspace\\mosc-temp\\mosc_downloads\\malankara-association-2022-2027\\2022\\Ankamaly-1-1.pdf"
    },
    {
      "index": 98,
      "ok": true,
      "skipped": "exists",
      "dest": "f:\\project_workspace\\mosc-temp\\mosc_downloads\\malankara-association-2022-2027\\2022\\Ankamaly.pdf"
    },
    {
      "index": 99,
      "ok": true,
      "skipped": "exists",
      "dest": "f:\\project_workspace\\mosc-temp\\mosc_downloads\\malankara-association-2022-2027\\2022\\Association-Kalpana-47-2022-2.pdf"
    },
    {
      "index": 100,
      "ok": true,
      "skipped": "exists",
      "dest": "f:\\project_workspace\\mosc-temp\\mosc_downloads\\malankara-association-2022-2027\\2022\\Association-Kalpana-English-2.pdf"
    },
    {
      "index": 101,
      "ok": true,
      "skipped": "exists",
      "dest": "f:\\project_workspace\\mosc-temp\\mosc_downloads\\malankara-association-2022-2027\\2022\\Bangalore-2.pdf"
    },
    {
      "index": 102,
      "ok": true,
      "skipped": "exists",
      "dest": "f:\\project_workspace\\mosc-temp\\mosc_downloads\\malankara-association-2022-2027\\2022\\Bangalore.pdf"
    },
    {
      "index": 103,
      "ok": true,
      "skipped": "exists",
      "dest": "f:\\project_workspace\\mosc-temp\\mosc_downloads\\malankara-association-2022-2027\\2022\\Bombay-3.pdf"
    },
    {
      "index": 104,
      "ok": true,
      "skipped": "exists",
      "dest": "f:\\project_workspace\\mosc-temp\\mosc_downloads\\malankara-association-2022-2027\\2022\\Bombay.pdf"
    },
    {
      "index": 105,
      "ok": true,
      "skipped": "exists",
      "dest": "f:\\project_workspace\\mosc-temp\\mosc_downloads\\malankara-association-2022-2027\\2022\\Brahamavar-3.pdf"
    },
    {
      "index": 106,
      "ok": true,
      "skipped": "exists",
      "dest": "f:\\project_workspace\\mosc-temp\\mosc_downloads\\malankara-association-2022-2027\\2022\\Brahamavar.pdf"
    },
    {
      "index": 107,
      "ok": true,
      "skipped": "exists",
      "dest": "f:\\project_workspace\\mosc-temp\\mosc_downloads\\malankara-association-2022-2027\\2022\\Calcutta-3.pdf"
    },
    {
      "index": 108,
      "ok": true,
      "skipped": "exists",
      "dest": "f:\\project_workspace\\mosc-temp\\mosc_downloads\\malankara-association-2022-2027\\2022\\Calcutta.pdf"
    },
    {
      "index": 109,
      "ok": true,
      "skipped": "exists",
      "dest": "f:\\project_workspace\\mosc-temp\\mosc_downloads\\malankara-association-2022-2027\\2022\\Chengannur-1.pdf"
    },
    {
      "index": 110,
      "ok": true,
      "skipped": "exists",
      "dest": "f:\\project_workspace\\mosc-temp\\mosc_downloads\\malankara-association-2022-2027\\2022\\Chengannur-4.pdf"
    },
    {
      "index": 111,
      "ok": true,
      "skipped": "exists",
      "dest": "f:\\project_workspace\\mosc-temp\\mosc_downloads\\malankara-association-2022-2027\\2022\\Delhi-2.pdf"
    },
    {
      "index": 112,
      "ok": true,
      "skipped": "exists",
      "dest": "f:\\project_workspace\\mosc-temp\\mosc_downloads\\malankara-association-2022-2027\\2022\\Delhi.pdf"
    },
    {
      "index": 113,
      "ok": true,
      "skipped": "exists",
      "dest": "f:\\project_workspace\\mosc-temp\\mosc_downloads\\malankara-association-2022-2027\\2022\\Election-Ariyeppu-Forum.pdf"
    },
    {
      "index": 114,
      "ok": true,
      "skipped": "exists",
      "dest": "f:\\project_workspace\\mosc-temp\\mosc_downloads\\malankara-association-2022-2027\\2022\\Final-Agenda.pdf"
    },
    {
      "index": 115,
      "ok": true,
      "skipped": "exists",
      "dest": "f:\\project_workspace\\mosc-temp\\mosc_downloads\\malankara-association-2022-2027\\2022\\Form-A-B.pdf"
    },
    {
      "index": 116,
      "ok": true,
      "skipped": "exists",
      "dest": "f:\\project_workspace\\mosc-temp\\mosc_downloads\\malankara-association-2022-2027\\2022\\Idukky-3.pdf"
    },
    {
      "index": 117,
      "ok": true,
      "skipped": "exists",
      "dest": "f:\\project_workspace\\mosc-temp\\mosc_downloads\\malankara-association-2022-2027\\2022\\Idukky.pdf"
    },
    {
      "index": 118,
      "ok": true,
      "skipped": "exists",
      "dest": "f:\\project_workspace\\mosc-temp\\mosc_downloads\\malankara-association-2022-2027\\2022\\Kalpana-No.-197-2022.pdf"
    },
    {
      "index": 119,
      "ok": true,
      "skipped": "exists",
      "dest": "f:\\project_workspace\\mosc-temp\\mosc_downloads\\malankara-association-2022-2027\\2022\\Kandanad-East-2.pdf"
    },
    {
      "index": 120,
      "ok": true,
      "skipped": "exists",
      "dest": "f:\\project_workspace\\mosc-temp\\mosc_downloads\\malankara-association-2022-2027\\2022\\Kandanad-East.pdf"
    },
    {
      "index": 121,
      "ok": true,
      "skipped": "exists",
      "dest": "f:\\project_workspace\\mosc-temp\\mosc_downloads\\malankara-association-2022-2027\\2022\\Kandanad-West-3.pdf"
    },
    {
      "index": 122,
      "ok": true,
      "skipped": "exists",
      "dest": "f:\\project_workspace\\mosc-temp\\mosc_downloads\\malankara-association-2022-2027\\2022\\Kandanad-West.pdf"
    },
    {
      "index": 123,
      "ok": true,
      "skipped": "exists",
      "dest": "f:\\project_workspace\\mosc-temp\\mosc_downloads\\malankara-association-2022-2027\\2022\\Kochi-1-1.pdf"
    },
    {
      "index": 124,
      "ok": true,
      "skipped": "exists",
      "dest": "f:\\project_workspace\\mosc-temp\\mosc_downloads\\malankara-association-2022-2027\\2022\\Kochi.pdf"
    },
    {
      "index": 125,
      "ok": true,
      "skipped": "exists",
      "dest": "f:\\project_workspace\\mosc-temp\\mosc_downloads\\malankara-association-2022-2027\\2022\\Kollam-3.pdf"
    },
    {
      "index": 126,
      "ok": true,
      "skipped": "exists",
      "dest": "f:\\project_workspace\\mosc-temp\\mosc_downloads\\malankara-association-2022-2027\\2022\\Kollam.pdf"
    },
    {
      "index": 127,
      "ok": true,
      "skipped": "exists",
      "dest": "f:\\project_workspace\\mosc-temp\\mosc_downloads\\malankara-association-2022-2027\\2022\\Kottarakkara-Punalur-3.pdf"
    },
    {
      "index": 128,
      "ok": true,
      "skipped": "exists",
      "dest": "f:\\project_workspace\\mosc-temp\\mosc_downloads\\malankara-association-2022-2027\\2022\\Kottarakkara-Punalur.pdf"
    },
    {
      "index": 129,
      "ok": true,
      "skipped": "exists",
      "dest": "f:\\project_workspace\\mosc-temp\\mosc_downloads\\malankara-association-2022-2027\\2022\\Kottayam-2.pdf"
    },
    {
      "index": 130,
      "ok": true,
      "skipped": "exists",
      "dest": "f:\\project_workspace\\mosc-temp\\mosc_downloads\\malankara-association-2022-2027\\2022\\Kottayam-Central-1-1.pdf"
    },
    {
      "index": 131,
      "ok": true,
      "skipped": "exists",
      "dest": "f:\\project_workspace\\mosc-temp\\mosc_downloads\\malankara-association-2022-2027\\2022\\Kottayam-Central.pdf"
    },
    {
      "index": 132,
      "ok": true,
      "skipped": "exists",
      "dest": "f:\\project_workspace\\mosc-temp\\mosc_downloads\\malankara-association-2022-2027\\2022\\Kottayam.pdf"
    },
    {
      "index": 133,
      "ok": true,
      "skipped": "exists",
      "dest": "f:\\project_workspace\\mosc-temp\\mosc_downloads\\malankara-association-2022-2027\\2022\\Kunnamkulam-2.pdf"
    },
    {
      "index": 134,
      "ok": true,
      "skipped": "exists",
      "dest": "f:\\project_workspace\\mosc-temp\\mosc_downloads\\malankara-association-2022-2027\\2022\\Kunnamkulam.pdf"
    },
    {
      "index": 135,
      "ok": true,
      "skipped": "exists",
      "dest": "f:\\project_workspace\\mosc-temp\\mosc_downloads\\malankara-association-2022-2027\\2022\\Madras-3.pdf"
    },
    {
      "index": 136,
      "ok": true,
      "skipped": "exists",
      "dest": "f:\\project_workspace\\mosc-temp\\mosc_downloads\\malankara-association-2022-2027\\2022\\Madras.pdf"
    },
    {
      "index": 137,
      "ok": true,
      "skipped": "exists",
      "dest": "f:\\project_workspace\\mosc-temp\\mosc_downloads\\malankara-association-2022-2027\\2022\\Malabar-1-1.pdf"
    },
    {
      "index": 138,
      "ok": true,
      "skipped": "exists",
      "dest": "f:\\project_workspace\\mosc-temp\\mosc_downloads\\malankara-association-2022-2027\\2022\\Malabar.pdf"
    },
    {
      "index": 139,
      "ok": true,
      "skipped": "exists",
      "dest": "f:\\project_workspace\\mosc-temp\\mosc_downloads\\malankara-association-2022-2027\\2022\\Malankara-Association-English-Kalpana-2022.pdf"
    },
    {
      "index": 140,
      "ok": true,
      "skipped": "exists",
      "dest": "f:\\project_workspace\\mosc-temp\\mosc_downloads\\malankara-association-2022-2027\\2022\\Mavelikara-2.pdf"
    },
    {
      "index": 141,
      "ok": true,
      "skipped": "exists",
      "dest": "f:\\project_workspace\\mosc-temp\\mosc_downloads\\malankara-association-2022-2027\\2022\\Mavelikara.pdf"
    },
    {
      "index": 142,
      "ok": true,
      "skipped": "exists",
      "dest": "f:\\project_workspace\\mosc-temp\\mosc_downloads\\malankara-association-2022-2027\\2022\\Metropolitans-W.C-Members-2.pdf"
    },
    {
      "index": 143,
      "ok": true,
      "skipped": "exists",
      "dest": "f:\\project_workspace\\mosc-temp\\mosc_downloads\\malankara-association-2022-2027\\2022\\Metropolitans-W.C-Members.pdf"
    },
    {
      "index": 144,
      "ok": true,
      "skipped": "exists",
      "dest": "f:\\project_workspace\\mosc-temp\\mosc_downloads\\malankara-association-2022-2027\\2022\\Nilackal-2.pdf"
    },
    {
      "index": 145,
      "ok": true,
      "skipped": "exists",
      "dest": "f:\\project_workspace\\mosc-temp\\mosc_downloads\\malankara-association-2022-2027\\2022\\Nilackal.pdf"
    },
    {
      "index": 146,
      "ok": true,
      "skipped": "exists",
      "dest": "f:\\project_workspace\\mosc-temp\\mosc_downloads\\malankara-association-2022-2027\\2022\\Niranam-2.pdf"
    },
    {
      "index": 147,
      "ok": true,
      "skipped": "exists",
      "dest": "f:\\project_workspace\\mosc-temp\\mosc_downloads\\malankara-association-2022-2027\\2022\\Niranam.pdf"
    },
    {
      "index": 148,
      "ok": true,
      "skipped": "exists",
      "dest": "f:\\project_workspace\\mosc-temp\\mosc_downloads\\malankara-association-2022-2027\\2022\\No.-119-2022-Notice-Kalpana-Malankara-Association.pdf"
    },
    {
      "index": 149,
      "ok": true,
      "skipped": "exists",
      "dest": "f:\\project_workspace\\mosc-temp\\mosc_downloads\\malankara-association-2022-2027\\2022\\No.-120-H-G-Mar-Irenaios-Tribunal.pdf"
    },
    {
      "index": 150,
      "ok": true,
      "skipped": "exists",
      "dest": "f:\\project_workspace\\mosc-temp\\mosc_downloads\\malankara-association-2022-2027\\2022\\North-East-America-3.pdf"
    },
    {
      "index": 151,
      "ok": true,
      "skipped": "exists",
      "dest": "f:\\project_workspace\\mosc-temp\\mosc_downloads\\malankara-association-2022-2027\\2022\\North-East-America.pdf"
    },
    {
      "index": 152,
      "ok": true,
      "skipped": "exists",
      "dest": "f:\\project_workspace\\mosc-temp\\mosc_downloads\\malankara-association-2022-2027\\2022\\South-West-Americac-3.pdf"
    },
    {
      "index": 153,
      "ok": true,
      "skipped": "exists",
      "dest": "f:\\project_workspace\\mosc-temp\\mosc_downloads\\malankara-association-2022-2027\\2022\\South-West-Americac.pdf"
    },
    {
      "index": 154,
      "ok": true,
      "skipped": "exists",
      "dest": "f:\\project_workspace\\mosc-temp\\mosc_downloads\\malankara-association-2022-2027\\2022\\Sulthan-Bathery-3.pdf"
    },
    {
      "index": 155,
      "ok": true,
      "skipped": "exists",
      "dest": "f:\\project_workspace\\mosc-temp\\mosc_downloads\\malankara-association-2022-2027\\2022\\Sulthan-Bathery.pdf"
    },
    {
      "index": 156,
      "ok": true,
      "skipped": "exists",
      "dest": "f:\\project_workspace\\mosc-temp\\mosc_downloads\\malankara-association-2022-2027\\2022\\Thiruvananthapuram-3.pdf"
    },
    {
      "index": 157,
      "ok": true,
      "skipped": "exists",
      "dest": "f:\\project_workspace\\mosc-temp\\mosc_downloads\\malankara-association-2022-2027\\2022\\Thiruvananthapuram.pdf"
    },
    {
      "index": 158,
      "ok": true,
      "skipped": "exists",
      "dest": "f:\\project_workspace\\mosc-temp\\mosc_downloads\\malankara-association-2022-2027\\2022\\Thrissur-2.pdf"
    },
    {
      "index": 159,
      "ok": true,
      "skipped": "exists",
      "dest": "f:\\project_workspace\\mosc-temp\\mosc_downloads\\malankara-association-2022-2027\\2022\\Thrissur.pdf"
    },
    {
      "index": 160,
      "ok": true,
      "skipped": "exists",
      "dest": "f:\\project_workspace\\mosc-temp\\mosc_downloads\\malankara-association-2022-2027\\2022\\Thumpamon-3.pdf"
    },
    {
      "index": 161,
      "ok": true,
      "skipped": "exists",
      "dest": "f:\\project_workspace\\mosc-temp\\mosc_downloads\\malankara-association-2022-2027\\2022\\Thumpamon.pdf"
    },
    {
      "index": 162,
      "ok": true,
      "skipped": "exists",
      "dest": "f:\\project_workspace\\mosc-temp\\mosc_downloads\\malankara-association-2022-2027\\2022\\UK-Europe-Africa-4.pdf"
    },
    {
      "index": 163,
      "ok": true,
      "skipped": "exists",
      "dest": "f:\\project_workspace\\mosc-temp\\mosc_downloads\\malankara-association-2022-2027\\2022\\UK-Europe-Africa.pdf"
    },
    {
      "index": 164,
      "ok": true,
      "skipped": "exists",
      "dest": "f:\\project_workspace\\mosc-temp\\mosc_downloads\\malankara-association-2022-2027\\2022\\Vinjapanam.pdf"
    }
  ]
}